podman_compose.py
podman_compose-1.4.1.dist-info/licenses/LICENSE
podman_compose-1.4.1.dist-info/METADATA
podman_compose-1.4.1.dist-info/WHEEL
podman_compose-1.4.1.dist-info/entry_points.txt
podman_compose-1.4.1.dist-info/top_level.txt
podman_compose-1.4.1.dist-info/RECORD
