Metadata-Version: 2.4
Name: podman-compose
Version: 1.4.1
Summary: A script to run docker-compose.yml using podman
Home-page: https://github.com/containers/podman-compose
Author: Muayyad Alsadi
Author-email: alsadi@gmail.com
License: GPL-2.0-only
Keywords: podman,podman-compose
Classifier: Programming Language :: Python
Classifier: Programming Language :: Python :: 3
Classifier: Programming Language :: Python :: 3.9
Classifier: Programming Language :: Python :: 3.10
Classifier: Programming Language :: Python :: 3.11
Classifier: Programming Language :: Python :: 3.12
Classifier: Programming Language :: Python :: 3.13
Classifier: Intended Audience :: Developers
Classifier: Operating System :: OS Independent
Classifier: Development Status :: 3 - Alpha
Classifier: Topic :: Software Development :: Build Tools
Classifier: License :: OSI Approved :: GNU General Public License v2 (GPLv2)
License-File: LICENSE
Requires-Dist: pyyaml
Requires-Dist: python-dotenv
Provides-Extra: devel
Requires-Dist: ruff; extra == "devel"
Requires-Dist: pre-commit; extra == "devel"
Requires-Dist: coverage; extra == "devel"
Requires-Dist: parameterized; extra == "devel"
Dynamic: author
Dynamic: author-email
Dynamic: classifier
Dynamic: description
Dynamic: description-content-type
Dynamic: home-page
Dynamic: keywords
Dynamic: license
Dynamic: license-file
Dynamic: provides-extra
Dynamic: requires-dist
Dynamic: summary
